LICENSE
MANIFEST.in
README.md
setup.cfg
setup.py
agape/auth/__init__.py
agape/auth/admin.py
agape/auth/apps.py
agape/auth/models.py
agape/auth/permissions.py
agape/auth/serializers.py
agape/auth/settings.py
agape/auth/test_default.py
agape/auth/test_username_config.py
agape/auth/urls.py
agape/auth/views.py
agape_auth.egg-info/PKG-INFO
agape_auth.egg-info/SOURCES.txt
agape_auth.egg-info/dependency_links.txt
agape_auth.egg-info/requires.txt
agape_auth.egg-info/top_level.txt