Metadata-Version: 2.1
Name: agape-auth
Version: 3.0.6
Summary: Agape Authentication library.
Home-page: https://gitlab.com/maverik.software/agape
Author: Jeffrey Hallock
Author-email: maverik.software@gmail.com
License: MIT License
Platform: UNKNOWN
Classifier: Environment :: Web Environment
Classifier: Framework :: Django
Classifier: Intended Audience :: Developers
Classifier: Operating System :: OS Independent
Classifier: Programming Language :: Python
Classifier: Programming Language :: Python :: 3.4
Classifier: Programming Language :: Python :: 3.5
Classifier: Programming Language :: Python :: 3.6
Classifier: Topic :: Internet :: WWW/HTTP
